emergence_agent/__init__.py
emergence_agent/agent.py
emergence_agent/client.py
emergence_agent/decorators.py
emergence_agent/developer.py
emergence_agent/exceptions.py
emergence_agent/version.py
emergence_agent-0.1.0.dist-info/LICENSE
emergence_agent-0.1.0.dist-info/METADATA
emergence_agent-0.1.0.dist-info/WHEEL
emergence_agent-0.1.0.dist-info/entry_points.txt
emergence_agent-0.1.0.dist-info/top_level.txt
emergence_agent-0.1.0.dist-info/RECORD
