Metadata-Version: 2.1
Name: emergence-agent
Version: 0.1.0
Summary: Official Python SDK for building and deploying intelligent agents on the Emergence Platform
Home-page: https://github.com/emergence-platform/emergence-agent-sdk
Author: Emergence Platform Team
Author-email: Emergence Platform Team <developers@emergence-platform.com>
Maintainer-email: Emergence Platform Team <developers@emergence-platform.com>
License: MIT
Project-URL: Homepage, https://emergence-platform.com
Project-URL: Documentation, https://docs.emergence-platform.com/agent-sdk
Project-URL: Repository, https://github.com/emergence-platform/emergence-agent-sdk
Project-URL: Bug Reports, https://github.com/emergence-platform/emergence-agent-sdk/issues
Project-URL: Platform, https://app.emergence-platform.com
Keywords: emergence,agent,ai,platform,sdk,webhook,automation,integration,api,client,intelligent-agents
Platform: any
Classifier: Development Status :: 4 - Beta
Classifier: Intended Audience :: Developers
Classifier: Topic :: Software Development :: Libraries :: Python Modules
Classifier: Topic :: Internet :: WWW/HTTP :: HTTP Servers
Classifier: Topic :: Scientific/Engineering :: Artificial Intelligence
Classifier: License :: OSI Approved :: MIT License
Classifier: Programming Language :: Python :: 3
Classifier: Programming Language :: Python :: 3.8
Classifier: Programming Language :: Python :: 3.9
Classifier: Programming Language :: Python :: 3.10
Classifier: Programming Language :: Python :: 3.11
Classifier: Programming Language :: Python :: 3.12
Classifier: Operating System :: OS Independent
Classifier: Environment :: Web Environment
Classifier: Framework :: AsyncIO
Requires-Python: >=3.8
License-File: LICENSE
Requires-Dist: requests (>=2.31.0)
Requires-Dist: aiohttp (>=3.8.0)
Requires-Dist: pydantic (>=2.0.0)
Requires-Dist: typing-extensions (>=4.0.0)
Requires-Dist: PyJWT (>=2.8.0)
Requires-Dist: urllib3 (>=2.0.0)
Requires-Dist: python-dateutil (>=2.8.0)
Requires-Dist: python-dotenv (>=1.0.0)
Requires-Dist: cryptography (>=41.0.0)
Provides-Extra: all
Requires-Dist: pytest (>=7.0.0) ; extra == 'all'
Requires-Dist: pytest-asyncio (>=0.21.0) ; extra == 'all'
Requires-Dist: pytest-cov (>=4.0.0) ; extra == 'all'
Requires-Dist: black (>=23.0.0) ; extra == 'all'
Requires-Dist: flake8 (>=6.0.0) ; extra == 'all'
Requires-Dist: mypy (>=1.0.0) ; extra == 'all'
Requires-Dist: isort (>=5.12.0) ; extra == 'all'
Requires-Dist: pre-commit (>=3.0.0) ; extra == 'all'
Requires-Dist: flask (>=2.3.0) ; extra == 'all'
Requires-Dist: fastapi (>=0.100.0) ; extra == 'all'
Requires-Dist: uvicorn (>=0.23.0) ; extra == 'all'
Requires-Dist: celery (>=5.3.0) ; extra == 'all'
Requires-Dist: redis (>=4.6.0) ; extra == 'all'
Requires-Dist: emergence-agent[dev,examples] ; extra == 'all'
Provides-Extra: dev
Requires-Dist: pytest (>=7.0.0) ; extra == 'dev'
Requires-Dist: pytest-asyncio (>=0.21.0) ; extra == 'dev'
Requires-Dist: pytest-cov (>=4.0.0) ; extra == 'dev'
Requires-Dist: black (>=23.0.0) ; extra == 'dev'
Requires-Dist: flake8 (>=6.0.0) ; extra == 'dev'
Requires-Dist: mypy (>=1.0.0) ; extra == 'dev'
Requires-Dist: isort (>=5.12.0) ; extra == 'dev'
Requires-Dist: pre-commit (>=3.0.0) ; extra == 'dev'
Provides-Extra: examples
Requires-Dist: flask (>=2.3.0) ; extra == 'examples'
Requires-Dist: fastapi (>=0.100.0) ; extra == 'examples'
Requires-Dist: uvicorn (>=0.23.0) ; extra == 'examples'
Requires-Dist: celery (>=5.3.0) ; extra == 'examples'
Requires-Dist: redis (>=4.6.0) ; extra == 'examples'
